naucse_render/__init__.py
naucse_render/__main__.py
naucse_render/cli.py
naucse_render/compile.py
naucse_render/course.py
naucse_render/encode.py
naucse_render/lesson.py
naucse_render/load.py
naucse_render/markdown.py
naucse_render/notebook.py
naucse_render/page.py
naucse_render/templates.py
naucse_render-2.0.dist-info/LICENSE.MIT
naucse_render-2.0.dist-info/METADATA
naucse_render-2.0.dist-info/WHEEL
naucse_render-2.0.dist-info/top_level.txt
naucse_render-2.0.dist-info/RECORD
