Metadata-Version: 2.1
Name: naucse_render
Version: 2.0
Summary: Converts course material to naucse.python.cz API
Maintainer-email: Petr Viktorin <encukou@gmail.com>
License: MIT
Project-URL: repository, https://github.com/pyvec/naucse_render
Classifier: License :: OSI Approved :: MIT License
Classifier: Programming Language :: Python :: 3
Requires-Python: >=3.8
License-File: LICENSE.MIT
Requires-Dist: ansi2html
Requires-Dist: mistune <4,>=2.0.3
Requires-Dist: nbconvert <8.0,>=7.0
Requires-Dist: traitlets
Requires-Dist: click
Requires-Dist: PyYAML
Requires-Dist: Jinja2 >3.0
Requires-Dist: Pygments >=2.3.1
Requires-Dist: markupsafe
Requires-Dist: lxml
Provides-Extra: dev
Requires-Dist: pytest ; extra == 'dev'
